{"Attack":["https://storage.googleapis.com/prueba-d1c99.appspot.com/xinzhao_skin_27/AttackChampion.mp3","https://storage.googleapis.com/prueba-d1c99.appspot.com/xinzhao_skin_27/AttackChampion2.mp3","https://storage.googleapis.com/prueba-d1c99.appspot.com/xinzhao_skin_27/AttackChampion3.mp3","https://storage.googleapis.com/prueba-d1c99.appspot.com/xinzhao_skin_27/AttackChampion4.mp3","https://storage.googleapis.com/prueba-d1c99.appspot.com/xinzhao_skin_27/AttackChampion5.mp3","https://storage.googleapis.com/prueba-d1c99.appspot.com/xinzhao_skin_27/AttackChampion6.mp3"],"Basic":["https://storage.googleapis.com/prueba-d1c99.appspot.com/xinzhao_skin_27/Basic2cast.mp3","https://storage.googleapis.com/prueba-d1c99.appspot.com/xinzhao_skin_27/Basic2cast2.mp3","https://storage.googleapis.com/prueba-d1c99.appspot.com/xinzhao_skin_27/Basic2cast3.mp3","https://storage.googleapis.com/prueba-d1c99.appspot.com/xinzhao_skin_27/Basic2cast4.mp3"],"Critical":["https://storage.googleapis.com/prueba-d1c99.appspot.com/xinzhao_skin_27/Criticalcast.mp3","https://storage.googleapis.com/prueba-d1c99.appspot.com/xinzhao_skin_27/Criticalcast2.mp3","https://storage.googleapis.com/prueba-d1c99.appspot.com/xinzhao_skin_27/Criticalcast3.mp3","https://storage.googleapis.com/prueba-d1c99.appspot.com/xinzhao_skin_27/Criticalcast4.mp3"],"Death":["https://storage.googleapis.com/prueba-d1c99.appspot.com/xinzhao_skin_27/Death.mp3","https://storage.googleapis.com/prueba-d1c99.appspot.com/xinzhao_skin_27/Death2.mp3","https://storage.googleapis.com/prueba-d1c99.appspot.com/xinzhao_skin_27/Death3.mp3","https://storage.googleapis.com/prueba-d1c99.appspot.com/xinzhao_skin_27/Death4.mp3"],"E":["https://storage.googleapis.com/prueba-d1c99.appspot.com/xinzhao_skin_27/Ecast.mp3","https://storage.googleapis.com/prueba-d1c99.appspot.com/xinzhao_skin_27/Ecast2.mp3","https://storage.googleapis.com/prueba-d1c99.appspot.com/xinzhao_skin_27/Ecast3.mp3","https://storage.googleapis.com/prueba-d1c99.appspot.com/xinzhao_skin_27/Ecast4.mp3"],"Joke":["https://storage.googleapis.com/prueba-d1c99.appspot.com/xinzhao_skin_27/Joke.mp3"],"Laugh":["https://storage.googleapis.com/prueba-d1c99.appspot.com/xinzhao_skin_27/Laugh.mp3","https://storage.googleapis.com/prueba-d1c99.appspot.com/xinzhao_skin_27/Laugh2.mp3","https://storage.googleapis.com/prueba-d1c99.appspot.com/xinzhao_skin_27/Laugh3.mp3","https://storage.googleapis.com/prueba-d1c99.appspot.com/xinzhao_skin_27/Laugh4.mp3"],"Move":["https://storage.googleapis.com/prueba-d1c99.appspot.com/xinzhao_skin_27/MoveOrder.mp3","https://storage.googleapis.com/prueba-d1c99.appspot.com/xinzhao_skin_27/MoveOrder2.mp3","https://storage.googleapis.com/prueba-d1c99.appspot.com/xinzhao_skin_27/MoveOrder3.mp3","https://storage.googleapis.com/prueba-d1c99.appspot.com/xinzhao_skin_27/MoveOrder4.mp3","https://storage.googleapis.com/prueba-d1c99.appspot.com/xinzhao_skin_27/MoveOrder5.mp3","https://storage.googleapis.com/prueba-d1c99.appspot.com/xinzhao_skin_27/MoveOrder6.mp3","https://storage.googleapis.com/prueba-d1c99.appspot.com/xinzhao_skin_27/MoveOrder7.mp3","https://storage.googleapis.com/prueba-d1c99.appspot.com/xinzhao_skin_27/MoveOrder8.mp3","https://storage.googleapis.com/prueba-d1c99.appspot.com/xinzhao_skin_27/MoveOrder9.mp3"],"Q":["https://storage.googleapis.com/prueba-d1c99.appspot.com/xinzhao_skin_27/QThrust1OnCast.mp3","https://storage.googleapis.com/prueba-d1c99.appspot.com/xinzhao_skin_27/QThrust1OnCast2.mp3","https://storage.googleapis.com/prueba-d1c99.appspot.com/xinzhao_skin_27/QThrust1OnCast3.mp3","https://storage.googleapis.com/prueba-d1c99.appspot.com/xinzhao_skin_27/QThrust1OnCast4.mp3","https://storage.googleapis.com/prueba-d1c99.appspot.com/xinzhao_skin_27/QThrust2OnCast.mp3","https://storage.googleapis.com/prueba-d1c99.appspot.com/xinzhao_skin_27/QThrust2OnCast2.mp3","https://storage.googleapis.com/prueba-d1c99.appspot.com/xinzhao_skin_27/QThrust2OnCast3.mp3","https://storage.googleapis.com/prueba-d1c99.appspot.com/xinzhao_skin_27/QThrust2OnCast4.mp3","https://storage.googleapis.com/prueba-d1c99.appspot.com/xinzhao_skin_27/QThrust3OnCast.mp3","https://storage.googleapis.com/prueba-d1c99.appspot.com/xinzhao_skin_27/QThrust3OnCast2.mp3","https://storage.googleapis.com/prueba-d1c99.appspot.com/xinzhao_skin_27/QThrust3OnCast3.mp3","https://storage.googleapis.com/prueba-d1c99.appspot.com/xinzhao_skin_27/QThrust3OnCast4.mp3"],"R":["https://storage.googleapis.com/prueba-d1c99.appspot.com/xinzhao_skin_27/Rcast.mp3","https://storage.googleapis.com/prueba-d1c99.appspot.com/xinzhao_skin_27/Rcast2.mp3","https://storage.googleapis.com/prueba-d1c99.appspot.com/xinzhao_skin_27/Rcast3.mp3","https://storage.googleapis.com/prueba-d1c99.appspot.com/xinzhao_skin_27/Rcast4.mp3"],"Taunt":["https://storage.googleapis.com/prueba-d1c99.appspot.com/xinzhao_skin_27/Taunt.mp3"],"W":["https://storage.googleapis.com/prueba-d1c99.appspot.com/xinzhao_skin_27/Wcast.mp3","https://storage.googleapis.com/prueba-d1c99.appspot.com/xinzhao_skin_27/Wcast2.mp3","https://storage.googleapis.com/prueba-d1c99.appspot.com/xinzhao_skin_27/Wcast3.mp3","https://storage.googleapis.com/prueba-d1c99.appspot.com/xinzhao_skin_27/Wcast4.mp3"]}